<?xml version="1.0" encoding="utf-8"?>
<root>
  <!-- Nota Bene: You need to add a handler in the DescriptionAppender in the AstroTrains C# -->
  <!-- If both NumUnitsToSpawn and strengthToSpawn are > 0 then we first create NumUnitsToSpawn of the tagged units, then also create StrengthToSpawn of them -->
  <item name="ReinforceHunterFleet"
        fires_on_every_train="true"
        trains_needed_before_firing="-1"
        trains_to_send_before_firing="-1"
        trains_allowed_on_map="3"
        effect_type="SpawnUnits"
        num_units_to_spawn="0"
        strength_associated="1000.0"
        bonus_strength_per_aip="80.0"
        unit_tags_to_spawn="AstroTrainDepotHunterFleet"
        spawn_on_local_planet="true"
        depot_self_destructs_on_firing="false"
        min_intensity_to_enable="1"
        max_intensity_to_enable="5"
        faction_to_own_units="HunterFleet"
        trains_must_go_near_player="true"
        effect_multiplier_for_low_difficulty="0.5"
        effect_multiplier_for_medium_difficulty="1.0"
        effect_multiplier_for_high_difficulty="1.5"
        id="1"
        />
  <item name="ReinforceWardenFleet"
        fires_on_every_train="true"
        trains_needed_before_firing="-1"
        trains_to_send_before_firing="-1"
        trains_allowed_on_map="3"
        effect_type="SpawnUnits"
        num_units_to_spawn="0"
        strength_associated="1000.0"
        bonus_strength_per_aip="80.0"
        unit_tags_to_spawn="AstroTrainDepotWardenFleet"
        spawn_on_local_planet="true"
        depot_self_destructs_on_firing="false"
        min_intensity_to_enable="1"
        max_intensity_to_enable="5"
        faction_to_own_units="WardenFleet"
        trains_must_go_near_player="true"
        effect_multiplier_for_low_difficulty="0.5"
        effect_multiplier_for_medium_difficulty="1.0"
        effect_multiplier_for_high_difficulty="1.5"
        id="2"
        />
  
    <item name="SpawnNewStation"
        fires_on_every_train="false"
        trains_needed_before_firing="2"
        trains_to_send_before_firing="-1"
        trains_allowed_on_map="3"
        effect_type="SpawnUnits"
        num_units_to_spawn="1"
        strength_associated="0.0"
        unit_tags_to_spawn="AstroTrainStation"
        spawn_on_local_planet="false"
        depot_self_destructs_on_firing="false"
        min_intensity_to_enable="2"
        max_intensity_to_enable="10"
        faction_to_own_units="AstroTrains"
        trains_must_go_near_player="false"
        id="3"
        />
    <item name="BoostCPA"
        fires_on_every_train="true"
        trains_needed_before_firing="-1"
        trains_to_send_before_firing="-1"
        trains_allowed_on_map="3"
        effect_type="BudgetBoost"
        num_units_to_spawn="1"
        strength_associated="1000.0"
        bonus_strength_per_aip="80.0"
        budget_to_boost="CPA"
        unit_tags_to_spawn="AstroTrainStation"
        spawn_on_local_planet="false"
        depot_self_destructs_on_firing="false"
        min_intensity_to_enable="3"
        max_intensity_to_enable="7"
        faction_to_own_units="AI"
        trains_must_go_near_player="true"
        effect_multiplier_for_low_difficulty="0.5"
        effect_multiplier_for_medium_difficulty="1.0"
        effect_multiplier_for_high_difficulty="1.5"
        id="4"
        />
    <item name="BoostWave"
        fires_on_every_train="true"
        trains_needed_before_firing="-1"
        trains_to_send_before_firing="-1"
        trains_allowed_on_map="3"
        effect_type="BudgetBoost"
        num_units_to_spawn="1"
        strength_associated="1000.0"
        bonus_strength_per_aip="80.0"
        budget_to_boost="Wave"
        unit_tags_to_spawn="AstroTrainStation"
        spawn_on_local_planet="false"
        depot_self_destructs_on_firing="false"
        min_intensity_to_enable="3"
        max_intensity_to_enable="7"
        faction_to_own_units="AI"
        trains_must_go_near_player="true"
        effect_multiplier_for_low_difficulty="0.5"
        effect_multiplier_for_medium_difficulty="1.0"
        effect_multiplier_for_high_difficulty="1.5"
        id="5"
        />

  <item name="SpawnGolem"
        fires_on_every_train="false"
        trains_needed_before_firing="4"
        trains_to_send_before_firing="-1"
        trains_allowed_on_map="3"
        effect_type="SpawnUnits"
        num_units_to_spawn="1"
        strength_associated="0"
        unit_tags_to_spawn="AIGolem"
        spawn_on_local_planet="true"
        depot_self_destructs_on_firing="true"
        min_intensity_to_enable="7"
        max_intensity_to_enable="10"
        faction_to_own_units="AI"
        trains_must_go_near_player="false"
        id="6"
        />

  <item name="SpawnFortress"
        fires_on_every_train="false"
        trains_needed_before_firing="4"
        trains_to_send_before_firing="-1"
        trains_allowed_on_map="3"
        effect_type="SpawnUnits"
        num_units_to_spawn="1"
        strength_associated="0.0"
        unit_tags_to_spawn="Fortress"
        spawn_on_local_planet="true"
        depot_self_destructs_on_firing="true"
        min_intensity_to_enable="5"
        max_intensity_to_enable="10"
        faction_to_own_units="AI"
        trains_must_go_near_player="true"
        id="7"
        />
		
  <item name="SpawnDireGuardian"
        fires_on_every_train="false"
        trains_needed_before_firing="4"
        trains_to_send_before_firing="-1"
        trains_allowed_on_map="3"
        effect_type="SpawnUnits"
        num_units_to_spawn="1"
        strength_associated="0.0"
        unit_tags_to_spawn="DireGuardian"
        spawn_on_local_planet="true"
        depot_self_destructs_on_firing="true"
        min_intensity_to_enable="7"
        max_intensity_to_enable="10"
        faction_to_own_units="AI"
        trains_must_go_near_player="false"
        id="8"
        />
		
 <item name="BoostWormholeInvasion"
        fires_on_every_train="true"
        trains_needed_before_firing="-1"
        trains_to_send_before_firing="-1"
        trains_allowed_on_map="3"
        effect_type="BudgetBoost"
        num_units_to_spawn="1"
        strength_associated="1000.0"
        bonus_strength_per_aip="80.0"
        budget_to_boost="WormholeInvasion"
        unit_tags_to_spawn="AstroTrainStation"
        spawn_on_local_planet="false"
        depot_self_destructs_on_firing="false"
        min_intensity_to_enable="7"
        max_intensity_to_enable="10"
        faction_to_own_units="AI"
        trains_must_go_near_player="false"
        effect_multiplier_for_low_difficulty="0.5"
        effect_multiplier_for_medium_difficulty="1.0"
        effect_multiplier_for_high_difficulty="1.5"
        id="9"
        />
    <item name="SpawnAIWave"
        fires_on_every_train="true"
        trains_needed_before_firing="-1"
        trains_to_send_before_firing="-1"
        trains_allowed_on_map="3"
        effect_type="SpawnAIWave"
        strength_associated="500.0"
        bonus_strength_per_aip="30.0"
        spawn_on_local_planet="false"
        depot_self_destructs_on_firing="false"
        min_intensity_to_enable="1"
        max_intensity_to_enable="10"
        faction_to_own_units="AI"
        trains_must_go_near_player="true"
        effect_multiplier_for_low_difficulty="0.5"
        effect_multiplier_for_medium_difficulty="1.0"
        effect_multiplier_for_high_difficulty="1.5"
        id="10"
        />
		
  <item name="SpawnHunterKiller"
        fires_on_every_train="false"
        trains_needed_before_firing="6"
        trains_to_send_before_firing="-1"
        trains_allowed_on_map="3"
        effect_type="SpawnUnits"
        num_units_to_spawn="1"
        strength_associated="0.0"
        unit_tags_to_spawn="HunterKiller"
        spawn_on_local_planet="true"
        depot_self_destructs_on_firing="true"
        min_intensity_to_enable="8"
        max_intensity_to_enable="10"
        faction_to_own_units="AI"
        trains_must_go_near_player="false"
        id="11"
        />

  <item name="SpawnRavenousShadow"
        fires_on_every_train="false"
        trains_needed_before_firing="10"
        trains_to_send_before_firing="-1"
        trains_allowed_on_map="3"
        effect_type="SpawnUnits"
        num_units_to_spawn="1"
        strength_associated="0.0"
        unit_tags_to_spawn="RavenousShadow"
        spawn_on_local_planet="true"
        depot_self_destructs_on_firing="true"
        min_intensity_to_enable="10"
        max_intensity_to_enable="10"
        faction_to_own_units="AI"
        trains_must_go_near_player="false"
        id="12"
        />
  

  <item name="SpawnFenrirPrototype"
        fires_on_every_train="false"
        trains_needed_before_firing="5"
        trains_to_send_before_firing="-1"
        trains_allowed_on_map="3"
        effect_type="SpawnUnits"
        num_units_to_spawn="1"
        strength_associated="0.0"
        unit_tags_to_spawn="Fenrir"
        spawn_on_local_planet="true"
        depot_self_destructs_on_firing="true"
        min_intensity_to_enable="5"
        max_intensity_to_enable="10"
        faction_to_own_units="AI"
        trains_must_go_near_player="true"
        id="13"
        /> 		

  <item name="SpawnReanimatorPrototype"
        fires_on_every_train="false"
        trains_needed_before_firing="6"
        trains_to_send_before_firing="-1"
        trains_allowed_on_map="3"
        effect_type="SpawnUnits"
        num_units_to_spawn="1"
        strength_associated="0.0"
        unit_tags_to_spawn="Reanimator"
        spawn_on_local_planet="true"
        depot_self_destructs_on_firing="true"
        min_intensity_to_enable="8"
        max_intensity_to_enable="10"
        faction_to_own_units="AI"
        trains_must_go_near_player="false"
        id="14"
        />

  <item name="SpawnUmbraPrototype"
        fires_on_every_train="false"
        trains_needed_before_firing="6"
        trains_to_send_before_firing="-1"
        trains_allowed_on_map="3"
        effect_type="SpawnUnits"
        num_units_to_spawn="1"
        strength_associated="0.0"
        unit_tags_to_spawn="Umbra"
        spawn_on_local_planet="true"
        depot_self_destructs_on_firing="true"
        min_intensity_to_enable="8"
        max_intensity_to_enable="10"
        faction_to_own_units="AI"
        trains_must_go_near_player="false"
        id="15"
        />

  <item name="SpawnShellshockerPrototype"
        fires_on_every_train="false"
        trains_needed_before_firing="5"
        trains_to_send_before_firing="-1"
        trains_allowed_on_map="3"
        effect_type="SpawnUnits"
        num_units_to_spawn="1"
        strength_associated="0.0"
        unit_tags_to_spawn="Shellshocker"
        spawn_on_local_planet="true"
        depot_self_destructs_on_firing="true"
        min_intensity_to_enable="6"
        max_intensity_to_enable="10"
        faction_to_own_units="AI"
        trains_must_go_near_player="false"
        id="16"
        />

  <item name="SpawnCustodianPrototype"
        fires_on_every_train="false"
        trains_needed_before_firing="6"
        trains_to_send_before_firing="-1"
        trains_allowed_on_map="3"
        effect_type="SpawnUnits"
        num_units_to_spawn="1"
        strength_associated="0.0"
        unit_tags_to_spawn="Custodian"
        spawn_on_local_planet="true"
        depot_self_destructs_on_firing="true"
        min_intensity_to_enable="7"
        max_intensity_to_enable="10"
        faction_to_own_units="WardenFleet"
        trains_must_go_near_player="false"
        id="17"
        />

  <item name="SpawnWarspitePrototype"
        fires_on_every_train="false"
        trains_needed_before_firing="7"
        trains_to_send_before_firing="-1"
        trains_allowed_on_map="3"
        effect_type="SpawnUnits"
        num_units_to_spawn="1"
        strength_associated="0.0"
        unit_tags_to_spawn="WarspiteArtillery"
        spawn_on_local_planet="true"
        depot_self_destructs_on_firing="true"
        min_intensity_to_enable="9"
        max_intensity_to_enable="10"
        faction_to_own_units="AI"
        trains_must_go_near_player="false"
        id="18"
        /> 		
</root>
